pycalaos/__init__.py
pycalaos/client.py
pycalaos/discovery.py
pycalaos/item/__init__.py
pycalaos/item/common.py
pycalaos/item/io.py
pycalaos-0.0.29.dist-info/METADATA
pycalaos-0.0.29.dist-info/WHEEL
pycalaos-0.0.29.dist-info/licenses/LICENSE.txt
pycalaos-0.0.29.dist-info/RECORD
