Metadata-Version: 2.1
Name: pycalaos
Version: 0.0.29
Summary: Calaos home automation client library
Project-URL: Homepage, https://github.com/willoma/pycalaos
Project-URL: Repository, https://github.com/willoma/pycalaos.git
Author-email: Willow Maccagnoni <willow.maccagnoni@gmail.com>
License: MIT License
License-File: LICENSE.txt
Classifier: License :: OSI Approved :: MIT License
Classifier: Operating System :: OS Independent
Classifier: Programming Language :: Python :: 3
Requires-Python: >=3.11
Requires-Dist: netifaces
Requires-Dist: requests
